setup.py
BreakfastSerial/BreakfastSerial.py
BreakfastSerial/__init__.py
BreakfastSerial/components.py
BreakfastSerial/util.py
BreakfastSerial.egg-info/PKG-INFO
BreakfastSerial.egg-info/SOURCES.txt
BreakfastSerial.egg-info/dependency_links.txt
BreakfastSerial.egg-info/requires.txt
BreakfastSerial.egg-info/top_level.txt