Metadata-Version: 1.0
Name: BreakfastSerial
Version: 0.0.9
Summary: Python Framework for interacting with Arduino
Home-page: http://github.com/theycallmeswift/BreakfastSerial/
Author: Swift
Author-email: theycallmeswift@gmail.com
License: UNKNOWN
Keywords: arduino,firmata
Platform: UNKNOWN
